mcp_app/__init__.py
mcp_app/azure_pricing_mcp_server/__init__.py
mcp_app/azure_pricing_mcp_server/architecture_patterns.py
mcp_app/azure_pricing_mcp_server/helpers.py
mcp_app/azure_pricing_mcp_server/infrastructure_analyzer.py
mcp_app/azure_pricing_mcp_server/logging_config.py
mcp_app/azure_pricing_mcp_server/report_generator.py
mcp_app/azure_pricing_mcp_server/server.py
mcp_app/azure_pricing_mcp_server/web_scraper.py
8p_inc_azure_pricing_mcp_server-1.0.0.dist-info/METADATA
8p_inc_azure_pricing_mcp_server-1.0.0.dist-info/WHEEL
8p_inc_azure_pricing_mcp_server-1.0.0.dist-info/entry_points.txt
8p_inc_azure_pricing_mcp_server-1.0.0.dist-info/licenses/LICENSE
8p_inc_azure_pricing_mcp_server-1.0.0.dist-info/licenses/NOTICE
8p_inc_azure_pricing_mcp_server-1.0.0.dist-info/RECORD
