Metadata-Version: 2.4
Name: 8p-inc.azure-pricing-mcp-server
Version: 1.0.0
Summary: An Azure Labs Model Context Protocol (MCP) server for Azure pricing analysis
Project-URL: Homepage, https://github.com/8p-inc/azure-pricing-mcp-server
Project-URL: Documentation, https://github.com/8p-inc/azure-pricing-mcp-server/blob/main/README.md
Project-URL: Source, https://github.com/8p-inc/azure-pricing-mcp-server.git
Project-URL: Bug Tracker, https://github.com/8p-inc/azure-pricing-mcp-server/issues
Project-URL: Changelog, https://github.com/8p-inc/azure-pricing-mcp-server/blob/main/CHANGELOG.md
Author: 8P Inc
Author-email: Azure Pricing MCP <azure-pricing-mcp@8p-inc.com>
License: Apache-2.0
License-File: LICENSE
License-File: NOTICE
Classifier: License :: OSI Approved :: Apache Software License
Classifier: Operating System :: OS Independent
Classifier: Programming Language :: Python
Classifier: Programming Language :: Python :: 3
Classifier: Programming Language :: Python :: 3.10
Classifier: Programming Language :: Python :: 3.11
Classifier: Programming Language :: Python :: 3.12
Classifier: Programming Language :: Python :: 3.13
Requires-Python: >=3.10
Requires-Dist: azure-identity>=1.15.0
Requires-Dist: azure-mgmt-billing>=6.0.0
Requires-Dist: azure-mgmt-consumption>=10.0.0
Requires-Dist: bs4>=0.0.2
Requires-Dist: httpx>=0.25.0
Requires-Dist: lxml>=4.9.0
Requires-Dist: mcp[cli]>=1.6.0
Requires-Dist: pydantic>=2.10.6
Requires-Dist: pytest-asyncio>=0.23.0
Requires-Dist: pytest>=7.4.0
Requires-Dist: typing-extensions>=4.8.0
